{
  "build": {
    "dockerfile": "Dockerfile"
  },
  "runArgs": [],
  "mounts": [
    "source=${localEnv:HOME}${localEnv:USERPROFILE}/.ssh,target=/home/vscode/.ssh,readonly,type=bind"
  ],
  "remoteEnv": {
    "SSH_AUTH_SOCK": "${localEnv:SSH_AUTH_SOCK}"
  },
  "customizations": {
    "vscode": {
      "extensions": [
        "bierner.markdown-emoji",
        "ms-vscode.hexeditor",
        "ritwickdey.liveserver",
        "rust-lang.rust-analyzer",
        "smulyono.reveal",
        "streetsidesoftware.code-spell-checker",
        "esbenp.prettier-vscode",
        "dbaeumer.vscode-eslint",
        "hashicorp.terraform",
        "yy0931.vscode-sqlite3-editor"
      ]
    }
  }
}
